{
    "PlayerName": "Ghast_Noob",
    "Online": "Kh\u00f4ng",
    "ClientID": -4685262332578790936,
    "UUID": [],
    "XBoxAuthenticated": "Kh\u00f4ng",
    "LastIP": "113.22.139.48",
    "FirstJoin": "08-12-2017 18:50:04",
    "LastJoin": "10-12-2017 10:56:37",
    "JoinCount": 21,
    "KillCount": "0",
    "DeathCount": 13,
    "KickCount": 12,
    "BlocksBreaked": 5459,
    "BlocksPlaced": 1481,
    "ChatMessages": 477,
    "FishCount": "0",
    "EnterBedCount": "0",
    "EatCount": 1,
    "CraftCount": 651,
    "DroppedItems": 2
}