{
    "PlayerName": "icaro_gamer_yt",
    "Online": "Kh\u00f4ng",
    "ClientID": -1555993190165962312,
    "UUID": [],
    "XBoxAuthenticated": "Kh\u00f4ng",
    "LastIP": "186.226.185.146",
    "FirstJoin": "04-11-2017 02:09:24",
    "LastJoin": "04-11-2017 02:09:24",
    "JoinCount": "1",
    "KillCount": "0",
    "DeathCount": "0",
    "KickCount": "0",
    "BlocksBreaked": 24,
    "BlocksPlaced": 2,
    "ChatMessages": 7,
    "FishCount": "0",
    "EnterBedCount": "0",
    "EatCount": "0",
    "CraftCount": "0",
    "DroppedItems": "0"
}