{
    "PlayerName": "Snapbacklove",
    "Online": "C\u00f3",
    "ClientID": -2125856705343011948,
    "UUID": [],
    "XBoxAuthenticated": "Kh\u00f4ng",
    "LastIP": "73.252.77.150",
    "FirstJoin": "10-12-2017 06:01:51",
    "LastJoin": "10-12-2017 06:01:51",
    "JoinCount": "1",
    "KillCount": "0",
    "DeathCount": "0",
    "KickCount": "0",
    "BlocksBreaked": 229,
    "BlocksPlaced": 130,
    "ChatMessages": "0",
    "FishCount": "0",
    "EnterBedCount": "0",
    "EatCount": "0",
    "CraftCount": "0",
    "DroppedItems": "0"
}